{
	"name": "2. Die praktischen Erfindungen",
    "words": [
		{ "de": [ "das Leben erleichtern" ], "fr": [ "faciliter la vie" ] },
		{ "de": [ "das Röntgen" ], "fr": [ "la radiographie" ] },
		{ "de": [ "das Medikament" ], "fr": [ "le médicament" ] },
		{ "de": [ "die Impfung" ], "fr": [ "le vaccin" ] },
		{ "de": [ "die Prothese" ], "fr": [ "la prothèse" ] },
		{ "de": [ "die artifizielles Herz" ], "fr": [ "le cœur artificiel" ] },
		{ "de": [ "das Leben verlängern" ], "fr": [ "allonger l'espérance de vie" ] },
		{ "de": [ "die Gesundheit verbessern" ], "fr": [ "améliorer la santé" ] },
		{ "de": [ "Krankheiten heilen" ], "fr": [ "guérir les maladies" ] },
        { "de": [ "pflegen" ], "fr": [ "soigner" ] },
        
		{ "de": [ "ökologische Stoffe" ], "fr": [ "tissus écologiques" ] },
        { "de": [ "ergonomische Schuhe" ], "fr": [ "chaussures ergonomiques" ] },
        { "de": [ "die Kleidung" ], "fr": [ "les habits" ] },
		{ "de": [ "Kleidung aus Milchfaser" ], "fr": [ "vêtements en fibres de lait" ] },
		{ "de": [ "die Faser" ], "fr": [ "la fibre" ] },
		{ "de": [ "natürlich" ], "fr": [ "naturel" ] },
		{ "de": [ "antibakteriell" ], "fr": [ "antibactérien" ] },
		{ "de": [ "antiallergisch" ], "fr": [ "antiallergique" ] },
		{ "de": [ "mehr Komfort haben" ], "fr": [ "avoir plus de confort" ] },
		{ "de": [ "das Leben verbessern" ], "fr": [ "améliorer la vie" ] },
        { "de": [ "sich wohler fühlen" ], "fr": [ "se sentir mieux" ] },
        
		{ "de": [ "die öffentliche Verkehrsmittel" ], "fr": [ "les transports en commun" ] },
		{ "de": [ "das Flugzeug" ], "fr": [ "l'avion" ] },
        { "de": [ "das elektrisches Fahrrad" ], "fr": [ "le vélo électrique" ] },
        { "de": [ "der Airbag" ], "fr": [ "l'airbag" ] },
		{ "de": [ "das ABS System" ], "fr": [ "le système ABS" ] },
        { "de": [ "das autonome Auto" ], "fr": [ "la voiture autonome" ] },
		{ "de": [ "das Raumschiff" ], "fr": [ "le vaisseau spatial" ] },
        { "de": [ "die Rakete" ], "fr": [ "la fusée" ] },
        { "de": [ "sich schneller bewegen" ], "fr": [ "se déplacer plus vite" ] },
		{ "de": [ "Zeit gewinnen" ], "fr": [ "gagner du temps" ] },
        { "de": [ "weit reisen können" ], "fr": [ "pouvoir voyager loin" ] },
        { "de": [ "ergonomischer sein" ], "fr": [ "être plus ergonomique" ] },
		{ "de": [ "neue Horizonte eröffnen" ], "fr": [ "ouvrir de nouveaux horizons" ] },
        { "de": [ "mehr Unabhängigkeit haben" ], "fr": [ "avoir plus d'indépendance" ] },
        { "de": [ "mehr Sicherkeit haben" ], "fr": [ "avoir plus de sécurité" ] },

		{ "de": [ "die Wissenschaft" ], "fr": [ "la science" ] },
        { "de": [ "der Apparat", "das Gerät" ], "fr": [ "l'appareil" ] }
    ]
}